Workbook

Sheet 1_Premissas
A1: PLANILHA DE VIABILIDADE FINANCEIRA — REVENDEDOR USG PORTÁTIL | SOBRAL/CE
A2: Premissas por Cenário | Células em AZUL = valores editáveis | Células em PRETO = fórmulas automáticas
A4: DEFINIÇÃO DOS CENÁRIOS
A5: PREMISSA | B5: CONSERVADOR | C5: MODERADO ★ | D5: OTIMISTA | E5: UNIDADE | F5: FONTE / NOTA
A6: Vendas por mês (unidades) | B6: 2 | C6: 4 | D6: 8 | E6: un/mês
A7: Ticket médio por venda | B7: 35000 | C7: 40000 | D7: 50000 | E7: R$/un
A8: Margem bruta (%) | B8: 0.28 | C8: 0.3 | D8: 0.33 | E8: %
A9: Meses de carência/ramp-up | B9: 3 | C9: 2 | D9: 1 | E9: meses
A10: Taxa de conversão de visitas (%) | B10: 0.05 | C10: 0.12 | D10: 0.2 | E10: %
A11: Ciclo médio de venda (dias) | B11: 90 | C11: 60 | D11: 30 | E11: dias
A12: Receita de manutenção/acessórios | B12: 0 | C12: 3000 | D12: 8000 | E12: R$/mês
A14: CUSTOS FIXOS MENSAIS (editáveis)
A15: ITEM DE CUSTO | B15: CONSERVADOR | C15: MODERADO | D15: OTIMISTA | E15: UNIDADE | F15: FONTE / NOTA
A16: Responsável Técnico (RT) | B16: 800 | C16: 1200 | D16: 1500 | E16: R$/mês | F16: Farmacêutico ou eng. biomédico PJ
A17: Contador especializado em saúde | B17: 600 | C17: 800 | D17: 1000 | E17: R$/mês | F17: Obrigatório desde o 1º mês
A18: Marketing digital (LinkedIn/Insta) | B18: 800 | C18: 1500 | D18: 2500 | E18: R$/mês | F18: LinkedIn Ads + Instagram médico
A19: Armazenamento / logística | B19: 600 | C19: 1000 | D19: 1500 | E19: R$/mês | F19: Espaço climatizado + frete demo
A20: Telefone / internet / misc | B20: 400 | C20: 500 | D20: 700 | E20: R$/mês | F20: Comunicação operacional
A21: Taxa AFE / Vigilância Sanitária | B21: 100 | C21: 100 | D21: 100 | E21: R$/mês | F21: Rateio mensal de custos fixos
A22: Seguro de equipamentos (demo) | B22: 200 | C22: 400 | D22: 600 | E22: R$/mês | F22: Seguro do aparelho demonstração
A23: Outros fixos (escritório/misc) | B23: 300 | C23: 500 | D23: 800 | E23: R$/mês
A24: TOTAL CUSTOS FIXOS / MÊS | B24: ==SUM(B16:B23) | C24: ==SUM(C16:C23) | D24: ==SUM(D16:D23)
A26: INVESTIMENTO INICIAL (one-time)
A27: ITEM | B27: VALOR MÍNIMO | C27: VALOR MÉDIO | D27: VALOR MÁXIMO | E27: UNIDADE | F27: NOTAS
A28: Abertura empresa (LTDA/SLU) | B28: 1500 | C28: 2500 | D28: 4000 | E28: R$ | F28: Contabilidade + cartório + JUCEC
A29: AFE ANVISA (taxas e petições) | B29: 500 | C29: 1200 | D29: 2500 | E29: R$ | F29: Depende do porte da empresa
A30: Alvará Sanitário Municipal | B30: 300 | C30: 600 | D30: 1000 | E30: R$ | F30: VISA Sobral — inspeção local
A31: Responsável Técnico (setup) | B31: 0 | C31: 500 | D31: 1000 | E31: R$ | F31: Setup inicial de POPs e docs
A32: Equipamento demonstração (1 un) | B32: 25000 | C32: 35000 | D32: 50000 | E32: R$ | F32: USG portátil demo + sondas
A33: Capital de giro inicial | B33: 5000 | C33: 10000 | D33: 20000 | E33: R$ | F33: Reserva 3–4 meses de custo fixo
A34: Materiais de marketing | B34: 1000 | C34: 2000 | D34: 4000 | E34: R$ | F34: Folders, vídeos, site, demo kit
A35: Consultoria regulatória | B35: 0 | C35: 2000 | D35: 5000 | E35: R$ | F35: Stone Okamont ou similar
A36: TOTAL INVESTIMENTO INICIAL | B36: ==SUM(B28:B35) | C36: ==SUM(C28:C35) | D36: ==SUM(D28:D35)

Sheet 2_DRE_Moderado
A1: DRE PROJETADO — 12 MESES | CENÁRIO MODERADO (EDITÁVEL)
A2: Valores baseados nas premissas da aba '1_Premissas' — Cenário Moderado (coluna C)
A4: DEMONSTRATIVO DE RESULTADO | B4: Jan | C4: Fev | D4: Mar | E4: Abr | F4: Mai | G4: Jun | H4: Jul | I4: Ago | J4: Set | K4: Out | L4: Nov | M4: Dez | N4: TOTAL ANO 1
A5: ↓ PREMISSAS (editáveis aqui ou na aba Premissas)
A6: Unidades vendidas/mês | B6: ==ROUND('1_Premissas'!C7*0.4,0) | C6: ==ROUND('1_Premissas'!C7*0.4,0) | D6: ==ROUND('1_Premissas'!C7*0.7,0) | E6: ==ROUND('1_Premissas'!C7*1.0,0) | F6: ==ROUND('1_Premissas'!C7*1.0,0) | G6: ==ROUND('1_Premissas'!C7*1.0,0) | H6: ==ROUND('1_Premissas'!C7*1.0,0) | I6: ==ROUND('1_Premissas'!C7*1.0,0) | J6: ==ROUND('1_Premissas'!C7*1.0,0) | K6: ==ROUND('1_Premissas'!C7*1.0,0) | L6: ==ROUND('1_Premissas'!C7*1.0,0) | M6: ==ROUND('1_Premissas'!C7*1.0,0)
A7: Ticket médio (R$) | B7: =='1_Premissas'!C8 | C7: =='1_Premissas'!C8 | D7: =='1_Premissas'!C8 | E7: =='1_Premissas'!C8 | F7: =='1_Premissas'!C8 | G7: =='1_Premissas'!C8 | H7: =='1_Premissas'!C8 | I7: =='1_Premissas'!C8 | J7: =='1_Premissas'!C8 | K7: =='1_Premissas'!C8 | L7: =='1_Premissas'!C8 | M7: =='1_Premissas'!C8
A8: Margem bruta (%) | B8: =='1_Premissas'!C9 | C8: =='1_Premissas'!C9 | D8: =='1_Premissas'!C9 | E8: =='1_Premissas'!C9 | F8: =='1_Premissas'!C9 | G8: =='1_Premissas'!C9 | H8: =='1_Premissas'!C9 | I8: =='1_Premissas'!C9 | J8: =='1_Premissas'!C9 | K8: =='1_Premissas'!C9 | L8: =='1_Premissas'!C9 | M8: =='1_Premissas'!C9
A10: RECEITAS
A11: Receita USG portátil | B11: ==B6*B7 | C11: ==C6*C7 | D11: ==D6*D7 | E11: ==E6*E7 | F11: ==F6*F7 | G11: ==G6*G7 | H11: ==H6*H7 | I11: ==I6*I7 | ... M11: ==M6*M7
A12: Receita manutenção/acessórios | B12: =='1_Premissas'!C11 | C12: =='1_Premissas'!C11 | D12: =='1_Premissas'!C11 | E12: =='1_Premissas'!C11 | F12: =='1_Premissas'!C11 | G12: =='1_Premissas'!C11 | H12: =='1_Premissas'!C11 | I12: =='1_Premissas'!C11 | J12: =='1_Premissas'!C11 | K12: =='1_Premissas'!C11 | L12: =='1_Premissas'!C11 | M12: =='1_Premissas'!C11
A13: RECEITA BRUTA TOTAL | B13: ==B11+B12 | C13: ==C11+C12 | D13: ==D11+D12 | E13: ==E11+E12 | F13: ==F11+F12 | G13: ==G11+G12 | H13: ==H11+H12 | I13: ==I11+I12 | ... M13: ==M11+M12 | N13: ==SUM(B13:M13)
A15: CUSTOS
A16: CMV — Custo da Mercadoria Vendida | B16: ==B11*(1-B8) | C16: ==C11*(1-C8) | D16: ==D11*(1-D8) | E16: ==E11*(1-E8) | F16: ==F11*(1-F8) | G16: ==G11*(1-G8) | H16: ==H11*(1-H8) | I16: ==I11*(1-I8) | ... M16: ==M11*(1-M8)
A17: Custos fixos totais | B17: =='1_Premissas'!C24 | C17: =='1_Premissas'!C24 | D17: =='1_Premissas'!C24 | E17: =='1_Premissas'!C24 | F17: =='1_Premissas'!C24 | G17: =='1_Premissas'!C24 | H17: =='1_Premissas'!C24 | I17: =='1_Premissas'!C24 | J17: =='1_Premissas'!C24 | K17: =='1_Premissas'!C24 | L17: =='1_Premissas'!C24 | M17: =='1_Premissas'!C24
A18: Impostos estimados (Simples ~9%) | B18: ==B13*0.09 | C18: ==C13*0.09 | D18: ==D13*0.09 | E18: ==E13*0.09 | F18: ==F13*0.09 | G18: ==G13*0.09 | H18: ==H13*0.09 | I18: ==I13*0.09 | ... M18: ==M13*0.09
A19: TOTAL CUSTOS E DESPESAS | B19: ==B16+B17+B18 | C19: ==C16+C17+C18 | D19: ==D16+D17+D18 | E19: ==E16+E17+E18 | F19: ==F16+F17+F18 | G19: ==G16+G17+G18 | H19: ==H16+H17+H18 | I19: ==I16+I17+I18 | ... M19: ==M16+M17+M18 | N19: ==SUM(B19:M19)
A21: RESULTADO
A22: Margem Bruta (R$) | B22: ==B11*B8 | C22: ==C11*C8 | D22: ==D11*D8 | E22: ==E11*E8 | F22: ==F11*F8 | G22: ==G11*G8 | H22: ==H11*H8 | I22: ==I11*I8 | ... M22: ==M11*M8 | N22: ==SUM(B22:M22)
A23: EBITDA (Lucro antes juros/depr.) | B23: ==B13-B17-B18 | C23: ==C13-C17-C18 | D23: ==D13-D17-D18 | E23: ==E13-E17-E18 | F23: ==F13-F17-F18 | G23: ==G13-G17-G18 | H23: ==H13-H17-H18 | I23: ==I13-I17-I18 | ... M23: ==M13-M17-M18 | N23: ==SUM(B23:M23)
A24: LUCRO LÍQUIDO (após CMV + fixos + imposto) | B24: ==B13-B19 | C24: ==C13-C19 | D24: ==D13-D19 | E24: ==E13-E19 | F24: ==F13-F19 | G24: ==G13-G19 | H24: ==H13-H19 | I24: ==I13-I19 | ... M24: ==M13-M19 | N24: ==SUM(B24:M24)
A25: Margem líquida (%) | B25: ==IF(B13=0,0,B24/B13) | C25: ==IF(C13=0,0,C24/C13) | D25: ==IF(D13=0,0,D24/D13) | E25: ==IF(E13=0,0,E24/E13) | F25: ==IF(F13=0,0,F24/F13) | G25: ==IF(G13=0,0,G24/G13) | H25: ==IF(H13=0,0,H24/H13) | I25: ==IF(I13=0,0,I24/I13) | ... N25: ==IF(N13=0,0,N24/N13)
A27: Fluxo de Caixa Acumulado | B27: ==-'1_Premissas'!C36+B24 | C27: ==B27+C24 | D27: ==C27+D24 | E27: ==D27+E24 | F27: ==E27+F24 | G27: ==F27+G24 | H27: ==G27+H24 | I27: ==H27+I24 | J27: ==I27+J24 | ... M27: ==L27+M24

Sheet 3_Comparativo_Cenarios
A1: COMPARATIVO — 3 CENÁRIOS DE VIABILIDADE
A3: INDICADOR | B3: CONSERVADOR | C3: MODERADO ★ | D3: OTIMISTA | E3: UNIDADE
A4: Vendas por mês (ano 1) | B4: =='1_Premissas'!B7 | C4: =='1_Premissas'!C7 | D4: =='1_Premissas'!D7 | E4: un/mês
A5: Ticket médio | B5: =='1_Premissas'!B8 | C5: =='1_Premissas'!C8 | D5: =='1_Premissas'!D8 | E5: R$
A6: Receita bruta mensal (steady) | B6: =='1_Premissas'!B7*'1_Premissas'!B8+'1_Premissas'!B11 | C6: =='1_Premissas'!C7*'1_Premissas'!C8+'1_Premissas'!C11 | D6: =='1_Premissas'!D7*'1_Premissas'!D8+'1_Premissas'!D11 | E6: R$/mês
A7: Custo fixo mensal | B7: =='1_Premissas'!B24 | C7: =='1_Premissas'!C24 | D7: =='1_Premissas'!D24 | E7: R$/mês
A8: Margem bruta % | B8: =='1_Premissas'!B9 | C8: =='1_Premissas'!C9 | D8: =='1_Premissas'!D9 | E8: %
A9: Margem bruta R$ (mensal steady) | B9: =='1_Premissas'!B7*'1_Premissas'!B8*'1_Premissas'!B9 | C9: =='1_Premissas'!C7*'1_Premissas'!C8*'1_Premissas'!C9 | D9: =='1_Premissas'!D7*'1_Premissas'!D8*'1_Premissas'!D9 | E9: R$/mês
A10: Impostos estimados (Simples ~9%) | B10: =='1_Premissas'!B7*'1_Premissas'!B8*0.09 | C10: =='1_Premissas'!C7*'1_Premissas'!C8*0.09 | D10: =='1_Premissas'!D7*'1_Premissas'!D8*0.09 | E10: R$/mês
A11: LUCRO LÍQUIDO MENSAL (steady) | B11: =='1_Premissas'!B7*'1_Premissas'!B8*'1_Premissas'!B9-'1_Premissas'!B24-'1_Premissas'!B7*'1_Premissas'!B8*0.09 | C11: =='1_Premissas'!C7*'1_Premissas'!C8*'1_Premissas'!C9-'1_Premissas'!C24-'1_Premissas'!C7*'1_Premissas'!C8*0.09 | D11: =='1_Premissas'!D7*'1_Premissas'!D8*'1_Premissas'!D9-'1_Premissas'!D24-'1_Premissas'!D7*'1_Premissas'!D8*0.09 | E11: R$/mês
A12: LUCRO LÍQUIDO ANUAL (est.) | B12: ==B11*10 | C12: ==C11*11 | D12: ==D11*12 | E12: R$/ano
A13: Investimento inicial (médio) | B13: =='1_Premissas'!B36 | C13: =='1_Premissas'!C36 | D13: =='1_Premissas'!D36 | E13: R$
A14: Payback estimado (meses) | B14: ==IF(B11<=0,"N/A",ROUND('1_Premissas'!B36/B11,1)) | C14: ==IF(C11<=0,"N/A",ROUND('1_Premissas'!C36/C11,1)) | D14: ==IF(D11<=0,"N/A",ROUND('1_Premissas'!D36/D11,1)) | E14: meses
A15: ROI anual (%) | B15: ==IF('1_Premissas'!B36=0,0,B12/'1_Premissas'!B36) | C15: ==IF('1_Premissas'!C36=0,0,C12/'1_Premissas'!C36) | D15: ==IF('1_Premissas'!D36=0,0,D12/'1_Premissas'!D36) | E15: %
A16: Ponto de equilíbrio (un/mês) | B16: ==CEILING('1_Premissas'!B24/('1_Premissas'!B8*('1_Premissas'!B9-0.09)),1) | C16: ==CEILING('1_Premissas'!C24/('1_Premissas'!C8*('1_Premissas'!C9-0.09)),1) | D16: ==CEILING('1_Premissas'!D24/('1_Premissas'!D8*('1_Premissas'!D9-0.09)),1) | E16: un/mês

Sheet 4_Credito_BNB_Sebrae
A1: LINHAS DE CRÉDITO — BNB / SEBRAE / PRONAMPE | CAPITAL DE GIRO E INVESTIMENTO
A2: Pesquisa realizada em abril/2026 — Verifique condições atualizadas com BNB e Sebrae antes de contratar
A4: LINHA DE CRÉDITO | B4: INSTITUIÇÃO | C4: TAXA JUROS | D4: PRAZO | E4: CARÊNCIA | F4: LIMITE | G4: FINALIDADE
A5: FNE Giro | B5: BNB | C5: a partir de 0,45%/mês | D5: até 36 meses | E5: até 3 meses | F5: Até R$ 16M (MPE) | G5: Capital de giro: estoques, mercadorias, insumos. Cobre aquisição de equipamentos demo.
A6: FNE MPE | B6: BNB | C6: a partir de 0,40%/mês | D6: até 12 anos | E6: até 4 anos | F6: Variável por análise | G6: Investimento fixo + capital de giro associado (40% do total). Ideal para equip. médicos.
A7: FNE Comércio e Serviços | B7: BNB | C7: a partir de 0,45%/mês | D7: até 10 anos | E7: até 3 anos | F7: Variável por análise | G7: Modernização e ampliação de comércios e serviços. Inclui equipamentos e capital de giro.
A8: PRONAMPE | B8: BNB/Caixa | C8: Selic + 6% a.a. | D8: até 48 meses | E8: até 11 meses | F8: Até R$ 250.000 | G8: Capital de giro puro. Para empresa <1 ano: até 50% do capital social.
A9: Giro Especial BNB | B9: BNB | C9: a partir de 0,56%/mês | D9: até 48 meses | E9: customizada | F9: Variável | G9: Capital de giro customizado ao fluxo de caixa da empresa.
A10: Crédito Assistido Caixa+FAMPE | B10: Sebrae/Caixa | C10: Taxas Caixa | D10: até 60 meses | E10: até 24 meses | F10: Variável | G10: Caixa + garantia FAMPE (até 80% do valor). Atendimento técnico gratuito Sebrae CE.
A11: FAMPE (garantia complementar) | B11: Sebrae | C11: Sem custo direto | D11: — | E11: — | F11: Até 80% do finan. | G11: Fundo de aval para complementar garantias junto a qualquer banco conveniado.
A12: Acredita Sebrae | B12: Sebrae/parceiros | C12: Variável | D12: até 60 meses | E12: até 24 meses | F12: Variável | G12: Crédito assistido + consultoria gratuita. Mais de R$11B viabilizados. Disponível CE.
A13: MPE Capital de Giro BNB | B13: BNB | C13: a partir de 0,45%/mês | D13: até 24 meses | E13: até 3 meses | F13: Variável | G13: Específico para reforço de capital de giro de micro e pequenas empresas.
A14: Conta Empresarial MPE | B14: BNB | C14: a partir de 2,86%/mês | D14: Rotativo | E14: — | F14: Até limite aprovado | G14: Cheque especial PJ. Usar somente para eventualidades — taxa mais alta.
A16: SIMULADOR DE PARCELA (editável)
A17: PARÂMETRO | B17: VALOR | D17: RESULTADO | E17: VALOR
A18: Valor do empréstimo (R$) | B18: 60000 | D18: Parcela mensal (após carência) | E18: ==IFERROR(PMT(B19,B20-B21,B18*(1+B19)^B21)*(-1),"Erro")
A19: Taxa de juros mensal (%) | B19: 0.006 | D19: Total pago ao banco | E19: ==IFERROR(B23*(B20-B21),"Erro")
A20: Prazo total (meses) | B20: 36 | D20: Total de juros pagos | E20: ==IFERROR(B24-B18,"Erro")
A21: Carência (meses) | B21: 3 | D21: Custo efetivo total (%a.a.) | E21: ==IFERROR((1+B19)^12-1,"Erro")
A27: CONTATOS BNB E SEBRAE — SOBRAL/CE
A28: INSTITUIÇÃO | B28: ENDEREÇO | C28: TELEFONE | D28: REFERÊNCIA | E28: SITE/PORTAL | F28: FONE GRATUITO
A29: BNB — Agência Sobral | B29: Av. Dom José, s/n — Centro | C29: (88) 3677-XXXX | D29: Ag. 0707 — Sobral CE | E29: bnb.gov.br | F29: 0800 728 3030
A30: Sebrae CE — Escritório Sobral | B30: R. João Távora, 80 — Centro | C30: (88) 3614-1690 | D30: sebrae.com.br/ce | E30: ce.sebrae.com.br | F30: 0800 570 0800
A31: BNB Digital | B31: App / Internet Banking | C31: — | D31: bnb.gov.br | E31: Simulador: bnb.gov.br/simuladores/fnegiro | F31: —
A32: Sebrae Acredita | B32: Portal Nacional | C32: — | D32: sebrae.com.br/acredita | E32: Acesso online + agência local | F32: —

Sheet 5_Fluxo_BreakEven
A1: FLUXO DE CAIXA PROJETADO + ANÁLISE DE BREAK-EVEN — 12 MESES
A3: ITEM | B3: Jan | C3: Fev | D3: Mar | E3: Abr | F3: Mai | G3: Jun | H3: Jul | I3: Ago | J3: Set | K3: Out | L3: Nov | M3: Dez | N3: TOTAL / ANO
A4: (+) Receita Bruta | B4: =='2_DRE_Moderado'!B13 | C4: =='2_DRE_Moderado'!C13 | D4: =='2_DRE_Moderado'!D13 | E4: =='2_DRE_Moderado'!E13 | F4: =='2_DRE_Moderado'!F13 | G4: =='2_DRE_Moderado'!G13 | H4: =='2_DRE_Moderado'!H13 | I4: =='2_DRE_Moderado'!I13 | ... M4: =='2_DRE_Moderado'!M13 | O4: ==SUM(B4:M4)
A5: (-) CMV | B5: ==-'2_DRE_Moderado'!B16 | C5: ==-'2_DRE_Moderado'!C16 | D5: ==-'2_DRE_Moderado'!D16 | E5: ==-'2_DRE_Moderado'!E16 | F5: ==-'2_DRE_Moderado'!F16 | G5: ==-'2_DRE_Moderado'!G16 | H5: ==-'2_DRE_Moderado'!H16 | I5: ==-'2_DRE_Moderado'!I16 | ... M5: ==-'2_DRE_Moderado'!M16 | O5: ==SUM(B5:M5)
A6: (-) Custos Fixos | B6: ==-'2_DRE_Moderado'!B17 | C6: ==-'2_DRE_Moderado'!C17 | D6: ==-'2_DRE_Moderado'!D17 | E6: ==-'2_DRE_Moderado'!E17 | F6: ==-'2_DRE_Moderado'!F17 | G6: ==-'2_DRE_Moderado'!G17 | H6: ==-'2_DRE_Moderado'!H17 | I6: ==-'2_DRE_Moderado'!I17 | ... M6: ==-'2_DRE_Moderado'!M17 | O6: ==SUM(B6:M6)
A7: (-) Impostos | B7: ==-'2_DRE_Moderado'!B18 | C7: ==-'2_DRE_Moderado'!C18 | D7: ==-'2_DRE_Moderado'!D18 | E7: ==-'2_DRE_Moderado'!E18 | F7: ==-'2_DRE_Moderado'!F18 | G7: ==-'2_DRE_Moderado'!G18 | H7: ==-'2_DRE_Moderado'!H18 | I7: ==-'2_DRE_Moderado'!I18 | ... M7: ==-'2_DRE_Moderado'!M18 | O7: ==SUM(B7:M7)
A8: (=) Caixa do Mês | B8: =='2_DRE_Moderado'!B24 | C8: =='2_DRE_Moderado'!C24 | D8: =='2_DRE_Moderado'!D24 | E8: =='2_DRE_Moderado'!E24 | F8: =='2_DRE_Moderado'!F24 | G8: =='2_DRE_Moderado'!G24 | H8: =='2_DRE_Moderado'!H24 | I8: =='2_DRE_Moderado'!I24 | ... M8: =='2_DRE_Moderado'!M24 | O8: ==SUM(B8:M8)
A10: Caixa Acumulado (após invest. inicial) | B10: ==-'1_Premissas'!C36+B8 | C10: ==B10+C8 | D10: ==C10+D8 | E10: ==D10+E8 | F10: ==E10+F8 | G10: ==F10+G8 | H10: ==G10+H8 | I10: ==H10+I8 | J10: ==I10+J8 | ... M10: ==L10+M8
A12: ANÁLISE DE BREAK-EVEN (PONTO DE EQUILÍBRIO)
A13: Custo fixo mensal (R$) | C13: =='1_Premissas'!C24
A14: Imposto efetivo sobre receita | C14: ==0.09
A15: Ticket médio (R$) | C15: =='1_Premissas'!C8
A16: Margem bruta (%) | C16: =='1_Premissas'!C9
A17: Contribuição marginal por un (R$) | C17: ==C16*C17-C16*C15
A18: BREAK-EVEN (unidades/mês) | C18: ==CEILING(C13/(C17*C15-C14*C15),1)
A19: BREAK-EVEN (receita/mês R$) | C19: ==C18*C15
A20: Margem de segurança (over B/E) | C20: =='1_Premissas'!C7-C18

Sheet 6_CRM_Clientes
A1: CRM SIMPLIFICADO — PIPELINE DE VENDAS USG PORTÁTIL | SOBRAL/CE
A3: # | B3: NOME DO CLIENTE / CLÍNICA | C3: MÉDICO RESPONSÁVEL | D3: ESPECIALIDADE | E3: TELEFONE | F3: E-MAIL / INSTA | G3: ESTÁGIO | H3: VALOR EST. (R$) | I3: PRÓXIMA AÇÃO | J3: DATA
A4: 1 | B4: Hospital Regional Norte (HRN) | C4: UTI / Plantonistas | D4: Intensivismo | E4: (88) 3677-9300 | F4: — | G4: Prospecção | H4: 50000 | I4: Contato direto Dr. [seu nome] | J4: Abr/2026
A5: 2 | B5: Santa Casa de Misericórdia | C5: Gestão hospitalar | D5: Multiprofissional | E5: (88) 3112-0400 | F5: — | G5: Prospecção | H5: 80000 | I5: Reunião c/ gerência médica | J5: Abr/2026
A6: 3 | B6: CLINICOR — Dra. Margleicia | C6: Dra. Margleicia Coutinho | D6: Cardio + Intensivismo | E6: (88) 3613-2244 | F6: — | G6: Demo agendada | H6: 38000 | I6: Demo Butterfly iQ+ no consultório | J6: Mai/2026
A7: 4 | B7: Centrocardio — Dr. Maurício | C7: Dr. Maurício Medeiros | D7: Cardiologia + Eco | E7: (88) 99722-5000 | F7: — | G7: Demo agendada | H7: 45000 | I7: Demonstração Mindray MX6 | J7: Mai/2026
A8: 5 | B8: Clínica do Coração de Sobral | C8: — | D8: Cardiologia | E8: (88) 97602-9250 | F8: — | G8: Prospecção | H8: 40000 | I8: Enviar material técnico | J8: Mai/2026
A9: 6 | B9: NOTRE — Ortopedia | C9: Dr. João Paulo Linhares | D9: Ortopedia + MSK | E9: — | F9: — | G9: Prospecção | H9: 35000 | I9: Visita + folder USG MSK | J9: Jun/2026
A10: 7 | B10: Clínica Santa Clara | C10: Dr. Tarciano | D10: Gineco/Obstetrícia | E10: (88) 3611-4610 | F10: — | G10: Prospecção | H10: 32000 | I10: Demo USG obstétrico | J10: Jun/2026
A11: 8 | B11: PrevMédica | C11: — | D11: Multi | E11: (88) 3613-2949 | F11: — | G11: Prospecção | H11: 35000 | I11: Contato com gerência | J11: Jun/2026
A12: 9 | B12: CMS Centro Médico Sobralense | C12: Dr. Luis Edmundo Furtado | D12: Neurologia | E12: (88) 99868-4795 | F12: — | G12: Prospecção | H12: 38000 | I12: Enviar proposta | J12: Jun/2026
A13: 10 | B13: Vila Clinic | C13: — | D13: Gastro/Gineco/Nefrologia | E13: (88) 99944-1702 | F13: — | G13: Prospecção | H13: 35000 | I13: Visita + folheto | J13: Jul/2026
A35: TOTAIS PIPELINE | H35: ==SUMIF(G4:G34,"Ganho ✅",H4:H34) | I35: ← Valor total GANHO
